variables_info/__init__.py
variables_info/core.py
variables_info-0.1.dist-info/METADATA
variables_info-0.1.dist-info/WHEEL
variables_info-0.1.dist-info/top_level.txt
variables_info-0.1.dist-info/RECORD
