Metadata-Version: 2.1
Name: variables-info
Version: 0.1
Summary: Print a lot of info about the content of variables
Home-page: https://github.com/Habimm/create_trace
Author: Dimitri Rusin
Author-email: dimitri@habimm.com
Classifier: License :: OSI Approved :: MIT License
Classifier: Programming Language :: Python :: 3
Classifier: Programming Language :: Python :: 3.6
Classifier: Programming Language :: Python :: 3.7
Classifier: Programming Language :: Python :: 3.8
Requires-Dist: colored
